easy_runner/__init__.py
easy_runner/runner.py
easy_runner-0.1.0.dist-info/LICENSE
easy_runner-0.1.0.dist-info/METADATA
easy_runner-0.1.0.dist-info/WHEEL
easy_runner-0.1.0.dist-info/top_level.txt
easy_runner-0.1.0.dist-info/RECORD
