Metadata-Version: 2.1
Name: easy-runner
Version: 0.1.0
Summary: A lightweight tool for managing and executing multiple parallel experiments.
Home-page: https://github.com/liuzuxin/easy-runner
Author: Zuxin Liu
Author-email: zuxin1997@gmail.com
License: MIT
Keywords: reinforcement learning platform pytorch
Classifier: Development Status :: 3 - Alpha
Classifier: Intended Audience :: Science/Research
Classifier: Topic :: Scientific/Engineering :: Artificial Intelligence
Classifier: Topic :: Software Development :: Libraries :: Python Modules
Classifier: License :: OSI Approved :: MIT License
Classifier: Programming Language :: Python :: 3.6
Classifier: Programming Language :: Python :: 3.7
Classifier: Programming Language :: Python :: 3.8
Classifier: Programming Language :: Python :: 3.9
Classifier: Programming Language :: Python :: 3.10
Requires-Python: >=3.6
License-File: LICENSE
Requires-Dist: prettytable (~=3.7.0)
Requires-Dist: psutil (~=5.9.5)
